Workbook

Sheet Raw Data
A1: Date | B1: Vendor | C1: Category | D1: Sub_Category | E1: Description | F1: Amount | G1: Type | H1: Payment_Method
A2: 46023 | B2: Stripe | C2: Revenue | D2: Subscription | E2: Monthly SaaS subscription | F2: 35000 | G2: Revenue | H2: Bank Transfer
A3: 46024 | B3: AWS | C3: AWS | D3: Cloud Hosting | E3: AWS monthly hosting | F3: 4000 | G3: Expense | H3: Credit Card
A4: 46025 | B4: Slack | C4: Tools | D4: Communication Tool | E4: Slack subscription | F4: 2500 | G4: Expense | H4: UPI
A5: 46026 | B5: Google Ads | C5: Marketing | D5: Paid Ads | E5: Google ad campaign | F5: 6000 | G5: Expense | H5: Bank Transfer
A6: 46027 | B6: HR Agency | C6: Hiring | D6: Recruitment | E6: Hiring intern | F6: 7000 | G6: Expense | H6: Credit Card
A7: 46028 | B7: Stripe | C7: Revenue | D7: Subscription | E7: Pro plan subscriptions | F7: 42000 | G7: Revenue | H7: Bank Transfer
A8: 46029 | B8: AWS | C8: AWS | D8: Database | E8: Database hosting | F8: 3500 | G8: Expense | H8: UPI
A9: 46030 | B9: Zoom | C9: Tools | D9: Meeting Tool | E9: Zoom subscription | F9: 1800 | G9: Expense | H9: Credit Card
A10: 46031 | B10: Instagram Ads | C10: Marketing | D10: Social Media Ads | E10: Instagram campaign | F10: 5500 | G10: Expense | H10: Bank Transfer
A11: 46032 | B11: HR Agency | C11: Hiring | D11: Recruitment | E11: Developer hiring | F11: 6500 | G11: Expense | H11: Credit Card
A12: 46033 | B12: Stripe | C12: Revenue | D12: Subscription | E12: Enterprise client | F12: 48000 | G12: Revenue | H12: Bank Transfer
A13: 46034 | B13: AWS | C13: AWS | D13: Storage | E13: Cloud storage | F13: 4200 | G13: Expense | H13: UPI
... A46: 46067 | B46: Job Portal | C46: Hiring | D46: Recruitment | E46: HR hiring | F46: 6200 | G46: Expense | H46: Credit Card

Sheet Financial Master
A1: Financial Master
A3: Particulars | B3: Total
A4: Revenue | B4: =SUMIF('Raw Data'!G:G,"Revenue",'Raw Data'!F:F) -> 392000
A5: AWS Expense | B5: =+SUMIF('Raw Data'!C:C,"AWS",'Raw Data'!F:F) -> 35900
A6: Tools Expense | B6: =+SUMIF('Raw Data'!C:C,"Tools",'Raw Data'!F:F) -> 19800
A7: Marketing Expense | B7: =+SUMIF('Raw Data'!C:C,"Marketing",'Raw Data'!F:F) -> 51000
A8: Hiring Expense | B8: =+SUMIF('Raw Data'!C:C,"Hiring",'Raw Data'!F:F) -> 58000
A9: Total Expenses | B9: =+SUM(B5:B8) -> 164700
A10: Gross Profit | B10: =+B4-B9 -> 227300
A11: Burn Rate | B11: =+B9-B4 -> -227300
A12: Profit Margin % | B12: =+B10/B4 -> 0.57984694
A13: Average Revenue | B13: =AVERAGEIF('Raw Data'!G:G,"Revenue",'Raw Data'!F:F) -> 43555.556
A14: Average Expense | B14: =AVERAGEIF('Raw Data'!G:G,"Expense",'Raw Data'!F:F) -> 4575
A15: Highest Revenue | B15: =_xlfn.MAXIFS('Raw Data'!F:F,'Raw Data'!G:G,"Revenue") -> 50000
A16: Lowest Revenue | B16: =_xlfn.MINIFS('Raw Data'!F:F,'Raw Data'!G:G,"Revenue") -> 35000
A17: Highest Expense | B17: =_xlfn.MAXIFS('Raw Data'!F:F,'Raw Data'!G:G,"Expense") -> 7000
A18: Lowest Expense | B18: =_xlfn.MINIFS('Raw Data'!F:F,'Raw Data'!G:G,"Expense") -> 1700
A19: Revenue Transactions | B19: =+COUNTIF('Raw Data'!G:G,"Revenue") -> 9
A20: Expense Transactions | B20: =+COUNTIF('Raw Data'!G:G,"Expense") -> 36
A22: Summary
A24: KPI | B24: Value
A25: Total Revenue | B25: =+B4 -> 392000
A26: Total Expenses | B26: =+B9 -> 164700
A27: Net Profit | B27: =+B10 -> 227300
A28: Burn Rate | B28: =+B11 -> -227300
A29: Profit Margin | B29: =+B12 -> 0.57984694

Sheet Expense Tracker
A1: Expense Tracker
A3: Category | B3: Total Amount
A4: AWS | B4: =+SUMIF('Raw Data'!C:C,"AWS",'Raw Data'!F:F) -> 35900
A5: Tools | B5: =+SUMIF('Raw Data'!C:C,"Tools",'Raw Data'!F:F) -> 19800
A6: Marketing | B6: =+SUMIF('Raw Data'!C:C,"Marketing",'Raw Data'!F:F) -> 51000
A7: Hiring | B7: =+SUMIF('Raw Data'!C:C,"Hiring",'Raw Data'!F:F) -> 58000
A8: Total Expense | B8: =+SUM(B4:B7) -> 164700

Sheet Initial Metrics
A1: Initial Metrics
A3: Metric | B3: Value
A4: MRR | B4: =+'Financial Master'!B4/12 -> 32666.667
A5: CAC | B5: =+SUMIF('Raw Data'!C:C,"Marketing",'Raw Data'!F:F)/50 -> 1020
A6: LTV | B6: =+B4*12 -> 392000
A7: Burn Rate | B7: =+'Financial Master'!B11 -> -227300
A8: Customer Acquisition Cost Ratio | B8: =+B6/B5 -> 384.31373
A9: Revenue Growth Estimate | B9: =+('Financial Master'!B4-350000)/350000 -> 0.12
A10: Monthly Expense Ratio | B10: =+('Financial Master'!B9/'Financial Master'!B4) -> 0.42015306
A11: Profitability Ratio | B11: =+('Financial Master'!B10/'Financial Master'!B4) -> 0.57984694
A12: Average Revenue Per Transaction | B12: =+'Financial Master'!B4/'Financial Master'!B19 -> 43555.556
A13: Average Expense Per Transaction | B13: =+'Financial Master'!B9/'Financial Master'!B20 -> 4575
